authorizon/__init__.py
authorizon/api.py
authorizon/client.py
authorizon/constants.py
authorizon/enforcer.py
authorizon/logger.py
authorizon/markers.py
authorizon/resource.py
authorizon/resource_registry.py
authorizon/types.py
authorizon-0.0.4.dist-info/METADATA
authorizon-0.0.4.dist-info/WHEEL
authorizon-0.0.4.dist-info/top_level.txt
authorizon-0.0.4.dist-info/RECORD
