Metadata-Version: 2.1
Name: authorizon
Version: 0.0.4
Summary: authorizon python sdk
Home-page: UNKNOWN
Author: Or Weis, Asaf Cohen
Author-email: or@authorizon.com
License: UNKNOWN
Platform: UNKNOWN
Classifier: Operating System :: OS Independent
Classifier: Programming Language :: Python
Classifier: Programming Language :: Python :: 3
Classifier: Programming Language :: Python :: 3.8
Classifier: Programming Language :: Python :: 3.9
Requires-Python: >=3.8
Requires-Dist: requests (==2.24.0)
Requires-Dist: structlog
Requires-Dist: pydantic
